cancat-2.9.5.2.data/scripts/CanCat
cancat-2.9.5.2.data/scripts/J1939Cat
cancat-2.9.5.2.data/scripts/cancat2candump
cancat-2.9.5.2.data/scripts/cancat2pcap
cancat-2.9.5.2.data/scripts/candump2cancat
cancat-2.9.5.2.data/scripts/canmap
cancat-2.9.5.2.data/scripts/pcap2cancat
cancatlib/J1939db.py
cancatlib/__init__.py
cancatlib/iso_tp.py
cancatlib/j1939.py
cancatlib/j1939stack.py
cancatlib/ccp/__init__.py
cancatlib/ccp/ccp_follower.py
cancatlib/ccp/ccp_leader.py
cancatlib/ccp/test_ccp_follower.py
cancatlib/ccp/test_ccp_leader.py
cancatlib/ccp/utils.py
cancatlib/envi/__init__.py
cancatlib/envi/bits.py
cancatlib/envi/exc.py
cancatlib/scripts/__init__.py
cancatlib/scripts/cancat2candump.py
cancatlib/scripts/cancat2pcap.py
cancatlib/scripts/candump2cancat.py
cancatlib/scripts/canmap.py
cancatlib/scripts/pcap2cancat.py
cancatlib/test/__init__.py
cancatlib/test/run_ccp_tests.py
cancatlib/test/test_cancat.py
cancatlib/test/test_convert.py
cancatlib/test/test_j1939.py
cancatlib/test/test_messages.py
cancatlib/test/test_uds.py
cancatlib/test/data/__init__.py
cancatlib/test/data/candump_examples.py
cancatlib/uds/__init__.py
cancatlib/uds/did.py
cancatlib/uds/ecu.py
cancatlib/uds/test.py
cancatlib/uds/types.py
cancatlib/uds/utils.py
cancatlib/utils/__init__.py
cancatlib/utils/convert.py
cancatlib/utils/log.py
cancatlib/utils/types.py
cancatlib/vstruct/__init__.py
cancatlib/vstruct/bitfield.py
cancatlib/vstruct/builder.py
cancatlib/vstruct/cparse.py
cancatlib/vstruct/primitives.py
cancatlib/vstruct/constants/__init__.py
cancatlib/vstruct/constants/ntstatus.py
cancatlib/vstruct/defs/__init__.py
cancatlib/vstruct/defs/bmp.py
cancatlib/vstruct/defs/dns.py
cancatlib/vstruct/defs/elf.py
cancatlib/vstruct/defs/gif.py
cancatlib/vstruct/defs/ihex.py
cancatlib/vstruct/defs/inet.py
cancatlib/vstruct/defs/java.py
cancatlib/vstruct/defs/kdcom.py
cancatlib/vstruct/defs/minidump.py
cancatlib/vstruct/defs/pcap.py
cancatlib/vstruct/defs/pe.py
cancatlib/vstruct/defs/pptp.py
cancat-2.9.5.2.dist-info/LICENSE
cancat-2.9.5.2.dist-info/METADATA
cancat-2.9.5.2.dist-info/WHEEL
cancat-2.9.5.2.dist-info/top_level.txt
cancat-2.9.5.2.dist-info/RECORD
