Metadata-Version: 2.1
Name: cancat
Version: 2.9.5.2
Summary: Multi-purpose tool for interacting with Controller Area Networks (CAN) and SAE J1939
Home-page: https://github.com/atlas0fd00m/CanCat
Author: atlas of d00m and the GRIMM CyPhy team
Author-email: atlas@r4780y.com
License: UNKNOWN
Download-URL: https://github.com/atlas0fd00m/CanCat/archive/v2.9.5.2.tar.gz
Keywords: can,controller area network,automotive,j1939,hacking,reverse engineering
Platform: UNKNOWN
Classifier: Development Status :: 5 - Production/Stable
Classifier: Intended Audience :: Telecommunications Industry
Classifier: Topic :: Communications
Classifier: License :: OSI Approved :: BSD License
Classifier: Programming Language :: Python :: 3
Classifier: Programming Language :: Python :: 3.6
Classifier: Programming Language :: Python :: 3.7
Classifier: Programming Language :: Python :: 3.8
Classifier: Programming Language :: Python :: 3.9
Requires-Python: >=3.6
Requires-Dist: ipython
Requires-Dist: pyserial
Requires-Dist: pyusb
Requires-Dist: termcolor
Requires-Dist: future
Requires-Dist: six
